pobyaryan/__init__.py
pobyaryan/agent.py
pobyaryan/cli.py
pobyaryan/cmdtool.py
pobyaryan-0.1.0.dist-info/licenses/LICENSE
pobyaryan-0.1.0.dist-info/METADATA
pobyaryan-0.1.0.dist-info/WHEEL
pobyaryan-0.1.0.dist-info/entry_points.txt
pobyaryan-0.1.0.dist-info/top_level.txt
pobyaryan-0.1.0.dist-info/RECORD
