Metadata-Version: 2.4
Name: pobyaryan
Version: 0.1.0
Summary: PO — an AI command-line agent by ARYAN
Author: ARYAN KHOKALE
License: MIT License
Project-URL: Homepage, https://github.com/AryanKhokale/po_by_aryank
Project-URL: Issues, https://github.com/AryanKhokale/po_by_aryank
Keywords: AI,agent,cli,automation,genai
Classifier: Programming Language :: Python :: 3
Classifier: License :: OSI Approved :: MIT License
Classifier: Operating System :: OS Independent
Requires-Python: >=3.9
License-File: LICENSE
Requires-Dist: google-genai~=1.0
Dynamic: license-file
